yandex_rasp/__init__.py
yandex_rasp/api/__init__.py
yandex_rasp/api/api.py
yandex_rasp/api/exceptions.py
yandex.rasp-0.0.2.dist-info/LICENSE
yandex.rasp-0.0.2.dist-info/METADATA
yandex.rasp-0.0.2.dist-info/WHEEL
yandex.rasp-0.0.2.dist-info/top_level.txt
yandex.rasp-0.0.2.dist-info/RECORD
