Metadata-Version: 2.1
Name: yandex.rasp
Version: 0.0.2
Summary: A Python wrapper for Yandex.Schedules API
Home-page: https://github.com/mekicha/yandex-rasp-api
Author: Emeka Icha
Author-email: emeka.icha@gmail.com
License: UNKNOWN
Keywords: yandex yandex.rasp rest
Platform: UNKNOWN
Classifier: Intended Audience :: Developers
Classifier: Development Status :: 3 - Alpha
Classifier: Programming Language :: Python
Classifier: Programming Language :: Python :: 3
Classifier: License :: OSI Approved :: MIT License
Classifier: Operating System :: OS Independent
Requires-Dist: requests
